setup.py
isha_dist_probability/Binomialdistribution.py
isha_dist_probability/Gaussiandistribution.py
isha_dist_probability/Generaldistribution.py
isha_dist_probability/__init__.py
isha_dist_probability.egg-info/PKG-INFO
isha_dist_probability.egg-info/SOURCES.txt
isha_dist_probability.egg-info/dependency_links.txt
isha_dist_probability.egg-info/not-zip-safe
isha_dist_probability.egg-info/top_level.txt