Metadata-Version: 1.0
Name: isha-dist-probability
Version: 0.1
Summary: Gaussian and Binomial distributions
Home-page: UNKNOWN
Author: isha anand
Author-email: UNKNOWN
License: UNKNOWN
Platform: UNKNOWN
